{
    "input_path": "/home/yukai/project/MoDora/datasets/MMDA/2.pdf",
    "page_index": 1,
    "parsing_res_list": [
        {
            "block_label": "header",
            "block_content": "日川财证券",
            "block_bbox": [
                138.36329650878906,
                92.98003387451172,
                380.2454833984375,
                163.67022705078125
            ],
            "block_id": 0,
            "block_order": 1
        },
        {
            "block_label": "paragraph_title",
            "block_content": "川财证券",
            "block_bbox": [
                138.36329650878906,
                92.98003387451172,
                380.2454833984375,
                163.67022705078125
            ],
            "block_id": 2,
            "block_order": 3
        },
        {
            "block_label": "paragraph_title",
            "block_content": "研究所",
            "block_bbox": [
                137.60244750976562,
                619.948974609375,
                226.37672424316406,
                644.8060302734375
            ],
            "block_id": 3,
            "block_order": 4
        },
        {
            "block_label": "text",
            "block_content": "政出资兴办的证券公司,是全国首家由财政国债中介机构整体转制而成的专业证券公司。经过三十余载的变革与成长,现今公司已发展成为由中国华电集团资本控股有限公司、四川省国有资产经营投资管理有限责任公司、四川省水电投资经营集团有限公司等资本和实力雄厚的大型企业共同持股的证券公司。公司一贯秉承诚实守信、专业运作、健康发展的经营理念，矢志服务客户、服务社会，创造了良好的经济效益和社会效益；目前，公",
            "block_bbox": [
                136.6629180908203,
                215.60989379882812,
                1052.4605712890625,
                566.0552978515625
            ],
            "block_id": 4,
            "block_order": 5
        },
        {
            "block_label": "text",
            "block_content": "内一流学府。致力于为金融机构、企业集团和政府部门提供专业的研究、咨询和调研服",
            "block_bbox": [
                137.30738830566406,
                662.7603149414062,
                1046.772216796875,
                778.5018920898438
            ],
            "block_id": 5,
            "block_order": 6
        },
        {
            "block_label": "image",
            "block_content": "S ",
            "block_bbox": [
                486.6448059082031,
                852.0472412109375,
                699.3014526367188,
                1060.776611328125
            ],
            "block_id": 6,
            "block_order": 7
        }
    ],
    "model_settings": {
        "use_doc_preprocessor": true,
        "use_seal_recognition": false,
        "use_table_recognition": true,
        "use_formula_recognition": true,
        "use_chart_recognition": true,
        "use_region_detection": true,
        "format_block_content": false
    }
}