{
    "input_path": "/home/yukai/project/MoDora/datasets/MMDA/1.pdf",
    "page_index": 7,
    "parsing_res_list": [
        {
            "block_label": "text",
            "block_content": "(Autorite des Marches Financiers）发表声明，称加密数字资产衍生品必须受到欧盟金融改革规定的监管，相关规定已经于2018年1月1日生效。",
            "block_bbox": [
                108.77034759521484,
                231.28492736816406,
                1282.650146484375,
                397.6378173828125
            ],
            "block_id": 3,
            "block_order": 4
        },
        {
            "block_label": "text",
            "block_content": "要求数字资产衍生品不得出现在线上广告中。法国金融市场监管局依据的是欧盟新版《金融工具市场法规》[Marketsin Financial Instruments Directive(MiFID2)]，该监管框架内规定了必须受到监管的衍生工具，",
            "block_bbox": [
                107.6781997680664,
                484.7771911621094,
                1283.0535888671875,
                781.9204711914062
            ],
            "block_id": 4,
            "block_order": 5
        },
        {
            "block_label": "text",
            "block_content": "2017年12月11日，韩国监管机构开始禁止比特币衍生品。在韩国金融投资协会(KoreaFinancial InvestmentAssociation)通报监管机构命令后，准",
            "block_bbox": [
                109.2937240600586,
                931.785400390625,
                1283.129150390625,
                1097.3885498046875
            ],
            "block_id": 5,
            "block_order": 6
        },
        {
            "block_label": "text",
            "block_content": "日本金融服务管理局于2017年9月任命了一位数字资产监控主管，并成立了一个30人的团队来监管虚拟货币交易。此后不久，该监管机构给11家数",
            "block_bbox": [
                110.24877166748047,
                1273.9415283203125,
                1282.0853271484375,
                1439.134521484375
            ],
            "block_id": 6,
            "block_order": 7
        }
    ],
    "model_settings": {
        "use_doc_preprocessor": true,
        "use_seal_recognition": false,
        "use_table_recognition": true,
        "use_formula_recognition": true,
        "use_chart_recognition": true,
        "use_region_detection": true,
        "format_block_content": false
    }
}